amsdal_server/Third-Party Materials - AMSDAL Dependencies - License Notices.md
amsdal_server/__about__.py
amsdal_server/__init__.py
amsdal_server/py.typed
amsdal_server/server.py
amsdal_server/apps/__init__.py
amsdal_server/apps/router.py
amsdal_server/apps/classes/__init__.py
amsdal_server/apps/classes/errors.py
amsdal_server/apps/classes/router.py
amsdal_server/apps/classes/controllers/__init__.py
amsdal_server/apps/classes/controllers/class_create.py
amsdal_server/apps/classes/controllers/class_delete.py
amsdal_server/apps/classes/controllers/class_detail.py
amsdal_server/apps/classes/controllers/class_list.py
amsdal_server/apps/classes/mixins/__init__.py
amsdal_server/apps/classes/mixins/column_info_mixin.py
amsdal_server/apps/classes/mixins/model_class_info.py
amsdal_server/apps/classes/serializers/__init__.py
amsdal_server/apps/classes/serializers/class_info.py
amsdal_server/apps/classes/serializers/register_class.py
amsdal_server/apps/classes/services/__init__.py
amsdal_server/apps/classes/services/classes_api.py
amsdal_server/apps/common/__init__.py
amsdal_server/apps/common/authentication.py
amsdal_server/apps/common/depends.py
amsdal_server/apps/common/errors.py
amsdal_server/apps/common/otel.py
amsdal_server/apps/common/response.py
amsdal_server/apps/common/thumbnail.py
amsdal_server/apps/common/utils.py
amsdal_server/apps/common/error_handlers/__init__.py
amsdal_server/apps/common/error_handlers/class_not_found.py
amsdal_server/apps/common/error_handlers/invalid_auth.py
amsdal_server/apps/common/error_handlers/permission_error.py
amsdal_server/apps/common/error_handlers/validation_error_handler.py
amsdal_server/apps/common/middlewares/__init__.py
amsdal_server/apps/common/middlewares/logger.py
amsdal_server/apps/common/middlewares/response_event.py
amsdal_server/apps/common/middlewares/slack_middleware.py
amsdal_server/apps/common/middlewares/utils.py
amsdal_server/apps/common/mixins/__init__.py
amsdal_server/apps/common/mixins/permissions_mixin.py
amsdal_server-0.5.14.dist-info/METADATA
amsdal_server-0.5.14.dist-info/WHEEL
amsdal_server-0.5.14.dist-info/licenses/LICENSE.txt
amsdal_server-0.5.14.dist-info/RECORD
