Metadata-Version: 2.4
Name: amsdal_server
Version: 0.5.14
Summary: Rest API server for AMSDAL framework
Project-URL: Documentation, https://pypi.org/project/amsdal_server/#readme
Project-URL: Issues, https://pypi.org/project/amsdal_server/
Project-URL: Source, https://pypi.org/project/amsdal_server/
Author-email: "A. Michael Salem" <ams@amsdal.com>
License: AMSDAL End User License Agreement
License-File: LICENSE.txt
Classifier: Development Status :: 4 - Beta
Classifier: Programming Language :: Python
Classifier: Programming Language :: Python :: 3.11
Classifier: Programming Language :: Python :: 3.12
Classifier: Programming Language :: Python :: 3.13
Classifier: Programming Language :: Python :: Implementation :: CPython
Classifier: Programming Language :: Python :: Implementation :: PyPy
Requires-Python: <3.14,>=3.11
Requires-Dist: amsdal==0.5.*
Requires-Dist: asgi-correlation-id~=4.3
Requires-Dist: fastapi~=0.127
Requires-Dist: joblib==1.5.*
Requires-Dist: orjson~=3.11
Requires-Dist: pillow==11.3.*
Requires-Dist: pydantic-settings~=2.12
Requires-Dist: pydantic~=2.12
Requires-Dist: uvicorn~=0.23
Provides-Extra: otel
Requires-Dist: opentelemetry-distro==0.60b1; extra == 'otel'
Requires-Dist: opentelemetry-exporter-otlp==1.39.1; extra == 'otel'
Requires-Dist: opentelemetry-instrumentation-fastapi==0.60b1; extra == 'otel'
Requires-Dist: opentelemetry-instrumentation-logging==0.60b1; extra == 'otel'
Requires-Dist: opentelemetry-instrumentation-requests==0.60b1; extra == 'otel'
